[
    {
        "nombre": "123",
        "direccion": "123",
        "gerente": "123",
        "snack": "123",
        "salas": [
            {
                "numero": "123",
                "can_sillas": "123",
                "altura": "123",
                "encargado": "123",
                "funciones": [
                    {
                        "nombre": "123",
                        "clasificacion": "123",
                        "director": "123",
                        "genero": "123",
                        "año": "123"
                    }
                ]
            }
        ]
    },
    {
        "nombre": "qw",
        "direccion": "qw",
        "gerente": "qw",
        "snack": "qw",
        "salas": [
            {
                "numero": "qw",
                "can_sillas": "qw",
                "altura": "qw",
                "encargado": "qw",
                "funciones": [
                    {
                        "nombre": "qw",
                        "clasificacion": "qw",
                        "director": "qw",
                        "genero": "qw",
                        "año": "qw"
                    }
                ]
            }
        ]
    }
]